pyRipser.cp314t-win32.pyd
ripser/__init__.py
ripser/_version.py
ripser/pyRips.pxd
ripser/pyRipser.cpp
ripser/pyRipser.pyx
ripser/ripser.cpp
ripser/ripser.py
ripser-0.6.14.dist-info/licenses/LICENSE.txt
ripser-0.6.14.dist-info/METADATA
ripser-0.6.14.dist-info/WHEEL
ripser-0.6.14.dist-info/top_level.txt
ripser-0.6.14.dist-info/RECORD
