Metadata-Version: 2.4
Name: ripser
Version: 0.6.14
Summary: A Lean Persistent Homology Library for Python
Author-email: Chris Tralie <chris.tralie@gmail.com>, Nathaniel Saul <nat@riverasaul.com>
Maintainer-email: Chris Tralie <chris.tralie@gmail.com>, Nathaniel Saul <nat@riverasaul.com>, Michael Catanzaro <catanzaromj@pm.me>
Project-URL: Homepage, https://ripser.scikit-tda.org
Project-URL: Documentation, https://ripser.scikit-tda.org
Project-URL: Repository, https://github.com/scikit-tda/ripser.py
Project-URL: Issues, https://github.com/scikit-tda/ripser.py/issues
Project-URL: Changelog, https://github.com/scikit-tda/ripser.py/blob/master/RELEASE.txt
Keywords: topological data analysis,persistent homology,Rips filtration,algebraic topology,unsupervised learning,persistence diagrams
Classifier: Development Status :: 3 - Alpha
Classifier: Intended Audience :: Science/Research
Classifier: Intended Audience :: Education
Classifier: Intended Audience :: Financial and Insurance Industry
Classifier: Intended Audience :: Healthcare Industry
Classifier: Topic :: Scientific/Engineering :: Information Analysis
Classifier: Topic :: Scientific/Engineering :: Mathematics
Classifier: License :: OSI Approved :: MIT License
Classifier: Programming Language :: Python
License-File: LICENSE.txt
Requires-Dist: Cython
Requires-Dist: numpy
Requires-Dist: persim
Requires-Dist: scipy
Requires-Dist: scikit-learn
Provides-Extra: testing
Requires-Dist: pytest; extra == "testing"
Requires-Dist: pytest-cov; extra == "testing"
Provides-Extra: docs
Requires-Dist: sktda_docs_config; extra == "docs"
Requires-Dist: sphinx<8.2.0; extra == "docs"
Requires-Dist: jupyter; extra == "docs"
Requires-Dist: pillow; extra == "docs"
Provides-Extra: ruff
Requires-Dist: ruff<0.12.0; extra == "ruff"
Dynamic: license-file
